<?xml version="1.0" encoding="UTF-8"?>
<belief_sentiment_doc id="tree-5693fa9b0000000000000037">
  <belief_annotations>
    <relations>
      <relation ere_id="relm-789">
        <trigger offset="251" length="2">in</trigger>
        <beliefs>
          <belief type="cb" polarity="pos" sarcasm="no">
            <source ere_id="m-105" offset="122" length="15">EdwardBaiamonte</source>
          </belief>
        </beliefs>
      </relation>
      <relation ere_id="relm-799">
        <trigger offset="383" length="8">chairman</trigger>
        <beliefs>
          <belief type="cb" polarity="pos" sarcasm="no">
            <source ere_id="m-279" offset="92" length="7">jillian</source>
          </belief>
        </beliefs>
      </relation>
      <relation ere_id="relm-809">
        <trigger offset="464" length="3">for</trigger>
        <beliefs>
          <belief type="cb" polarity="pos" sarcasm="no">
            <source ere_id="m-279" offset="92" length="7">jillian</source>
          </belief>
        </beliefs>
      </relation>
      <relation ere_id="relm-819">
        <trigger offset="871" length="7">parents</trigger>
        <beliefs>
          <belief type="cb" polarity="pos" sarcasm="no">
            <source ere_id="m-123" offset="623" length="15">EdwardBaiamonte</source>
          </belief>
        </beliefs>
      </relation>
      <relation ere_id="relm-829">
        <trigger offset="5498" length="2">at</trigger>
        <beliefs>
          <belief type="cb" polarity="pos" sarcasm="no">
            <source ere_id="m-591" offset="5423" length="7">Oddball</source>
          </belief>
        </beliefs>
      </relation>
      <relation ere_id="relm-839">
        <trigger offset="5763" length="4">with</trigger>
        <beliefs>
          <belief type="cb" polarity="pos" sarcasm="no">
            <source ere_id="m-585" offset="5366" length="7">Oddball</source>
          </belief>
        </beliefs>
      </relation>
      <relation ere_id="relm-907">
        <trigger offset="338" length="8">Chairman</trigger>
        <beliefs>
          <belief type="na">
            <source ere_id="m-105" offset="122" length="15">EdwardBaiamonte</source>
          </belief>
        </beliefs>
      </relation>
      <relation ere_id="relm-1230">
        <trigger offset="1997" length="6">got to</trigger>
        <beliefs>
          <belief type="cb" polarity="pos" sarcasm="no">
            <source ere_id="m-537" offset="1712" length="8">samjones</source>
          </belief>
        </beliefs>
      </relation>
      <relation ere_id="relm-1240">
        <trigger offset="3240" length="6">got to</trigger>
        <beliefs>
          <belief type="cb" polarity="pos" sarcasm="no">
            <source ere_id="m-549" offset="2995" length="8">samjones</source>
          </belief>
        </beliefs>
      </relation>
      <relation ere_id="relm-1250">
        <trigger offset="3899" length="6">got to</trigger>
        <beliefs>
          <belief type="cb" polarity="pos" sarcasm="no">
            <source ere_id="m-555" offset="3654" length="8">samjones</source>
          </belief>
        </beliefs>
      </relation>
      <relation ere_id="relm-1260">
        <trigger offset="4644" length="6">got to</trigger>
        <beliefs>
          <belief type="cb" polarity="pos" sarcasm="no">
            <source ere_id="m-567" offset="4606" length="8">samjones</source>
          </belief>
        </beliefs>
      </relation>
      <relation ere_id="relm-1270">
        <trigger offset="7438" length="5">go to</trigger>
        <beliefs>
          <belief type="na">
            <source ere_id="m-501" offset="6805" length="4">DSGE</source>
          </belief>
        </beliefs>
      </relation>
    </relations>
    <events>
      <event ere_id="em-849">
        <trigger offset="369" length="7">appoint</trigger>
        <beliefs>
          <belief type="cb" polarity="pos" sarcasm="no">
            <source ere_id="m-279" offset="92" length="7">jillian</source>
          </belief>
        </beliefs>
        <arguments>
          <arg ere_id="m-351" offset="377" length="14">
            <text>a fed chairman</text>
            <beliefs>
              <belief type="cb" polarity="pos" sarcasm="no">
                <source ere_id="m-279" offset="92" length="7">jillian</source>
              </belief>
            </beliefs>
          </arg>
          <arg ere_id="m-327" offset="359" length="5">
            <text>obama</text>
            <beliefs>
              <belief type="cb" polarity="pos" sarcasm="no">
                <source ere_id="m-279" offset="92" length="7">jillian</source>
              </belief>
            </beliefs>
          </arg>
        </arguments>
      </event>
      <event ere_id="em-917">
        <trigger offset="515" length="3">pay</trigger>
        <beliefs>
          <belief type="na">
            <source ere_id="m-99" offset="14" length="15">EdwardBaiamonte</source>
          </belief>
        </beliefs>
        <arguments>
          <arg ere_id="m-117" offset="510" length="1">
            <text>I</text>
            <beliefs>
              <belief type="na">
                <source ere_id="m-99" offset="14" length="15">EdwardBaiamonte</source>
              </belief>
            </beliefs>
          </arg>
          <arg ere_id="m-285" offset="519" length="3">
            <text>you</text>
            <beliefs>
              <belief type="na">
                <source ere_id="m-99" offset="14" length="15">EdwardBaiamonte</source>
              </belief>
            </beliefs>
          </arg>
          <arg ere_id="f-951" offset="523" length="7">
            <text>$10,000</text>
            <beliefs>
              <belief type="na">
                <source ere_id="m-99" offset="14" length="15">EdwardBaiamonte</source>
              </belief>
            </beliefs>
          </arg>
        </arguments>
      </event>
      <event ere_id="em-1289">
        <trigger offset="303" length="7">appoint</trigger>
        <beliefs>
          <belief type="na">
            <source ere_id="m-279" offset="92" length="7">jillian</source>
          </belief>
        </beliefs>
        <arguments>
          <arg ere_id="m-901" offset="311" length="35">
            <text>a liberal inflationist Fed Chairman</text>
            <beliefs>
              <belief type="na">
                <source ere_id="m-279" offset="92" length="7">jillian</source>
              </belief>
            </beliefs>
          </arg>
          <arg ere_id="m-321" offset="285" length="5">
            <text>Obama</text>
            <beliefs>
              <belief type="na">
                <source ere_id="m-279" offset="92" length="7">jillian</source>
              </belief>
            </beliefs>
          </arg>
        </arguments>
      </event>
    </events>
  </belief_annotations>
  <sentiment_annotations>
    <entities>
      <entity ere_id="m-99" offset="14" length="15">
        <text>EdwardBaiamonte</text>
        <sentiments>
          <sentiment polarity="none" sarcasm="no"/>
        </sentiments>
      </entity>
      <entity ere_id="m-105" offset="122" length="15">
        <text>EdwardBaiamonte</text>
        <sentiments>
          <sentiment polarity="none" sarcasm="no"/>
        </sentiments>
      </entity>
      <entity ere_id="m-111" offset="493" length="1">
        <text>I</text>
        <sentiments>
          <sentiment polarity="none" sarcasm="no"/>
        </sentiments>
      </entity>
      <entity ere_id="m-117" offset="510" length="1">
        <text>I</text>
        <sentiments>
          <sentiment polarity="none" sarcasm="no"/>
        </sentiments>
      </entity>
      <entity ere_id="m-123" offset="623" length="15">
        <text>EdwardBaiamonte</text>
        <sentiments>
          <sentiment polarity="none" sarcasm="no"/>
        </sentiments>
      </entity>
      <entity ere_id="m-129" offset="958" length="15">
        <text>EdwardBaiamonte</text>
        <sentiments>
          <sentiment polarity="none" sarcasm="no"/>
        </sentiments>
      </entity>
      <entity ere_id="m-135" offset="1270" length="15">
        <text>EdwardBaiamonte</text>
        <sentiments>
          <sentiment polarity="none" sarcasm="no"/>
        </sentiments>
      </entity>
      <entity ere_id="m-141" offset="1503" length="6">
        <text>Edward</text>
        <sentiments>
          <sentiment polarity="none" sarcasm="no"/>
        </sentiments>
      </entity>
      <entity ere_id="m-147" offset="1783" length="15">
        <text>EdwardBaiamonte</text>
        <sentiments>
          <sentiment polarity="none" sarcasm="no"/>
        </sentiments>
      </entity>
      <entity ere_id="m-153" offset="2290" length="15">
        <text>EdwardBaiamonte</text>
        <sentiments>
          <sentiment polarity="none" sarcasm="no"/>
        </sentiments>
      </entity>
      <entity ere_id="m-159" offset="2483" length="6">
        <text>Edward</text>
        <sentiments>
          <sentiment polarity="none" sarcasm="no"/>
        </sentiments>
      </entity>
      <entity ere_id="m-165" offset="2917" length="15">
        <text>EdwardBaiamonte</text>
        <sentiments>
          <sentiment polarity="none" sarcasm="no"/>
        </sentiments>
      </entity>
      <entity ere_id="m-171" offset="3026" length="15">
        <text>EdwardBaiamonte</text>
        <sentiments>
          <sentiment polarity="none" sarcasm="no"/>
        </sentiments>
      </entity>
      <entity ere_id="m-177" offset="3616" length="15">
        <text>EdwardBaiamonte</text>
        <sentiments>
          <sentiment polarity="none" sarcasm="no"/>
        </sentiments>
      </entity>
      <entity ere_id="m-183" offset="3685" length="15">
        <text>EdwardBaiamonte</text>
        <sentiments>
          <sentiment polarity="none" sarcasm="no"/>
        </sentiments>
      </entity>
      <entity ere_id="m-189" offset="4197" length="3">
        <text>You</text>
        <sentiments>
          <sentiment polarity="none" sarcasm="no"/>
        </sentiments>
      </entity>
      <entity ere_id="m-195" offset="4463" length="15">
        <text>EdwardBaiamonte</text>
        <sentiments>
          <sentiment polarity="none" sarcasm="no"/>
        </sentiments>
      </entity>
      <entity ere_id="m-201" offset="4229" length="3">
        <text>you</text>
        <sentiments>
          <sentiment polarity="none" sarcasm="no"/>
        </sentiments>
      </entity>
      <entity ere_id="m-207" offset="4568" length="15">
        <text>EdwardBaiamonte</text>
        <sentiments>
          <sentiment polarity="none" sarcasm="no"/>
        </sentiments>
      </entity>
      <entity ere_id="m-213" offset="4942" length="3">
        <text>You</text>
        <sentiments>
          <sentiment polarity="none" sarcasm="no"/>
        </sentiments>
      </entity>
      <entity ere_id="m-219" offset="4974" length="3">
        <text>you</text>
        <sentiments>
          <sentiment polarity="none" sarcasm="no"/>
        </sentiments>
      </entity>
      <entity ere_id="m-225" offset="6872" length="15">
        <text>EdwardBaiamonte</text>
        <sentiments>
          <sentiment polarity="none" sarcasm="no"/>
        </sentiments>
      </entity>
      <entity ere_id="m-231" offset="6937" length="15">
        <text>EdwardBaiamonte</text>
        <sentiments>
          <sentiment polarity="none" sarcasm="no"/>
        </sentiments>
      </entity>
      <entity ere_id="m-237" offset="7070" length="3">
        <text>you</text>
        <sentiments>
          <sentiment polarity="none" sarcasm="no"/>
        </sentiments>
      </entity>
      <entity ere_id="m-243" offset="7523" length="3">
        <text>you</text>
        <sentiments>
          <sentiment polarity="none" sarcasm="no"/>
        </sentiments>
      </entity>
      <entity ere_id="m-249" offset="7399" length="3">
        <text>you</text>
        <sentiments>
          <sentiment polarity="none" sarcasm="no"/>
        </sentiments>
      </entity>
      <entity ere_id="m-255" offset="7569" length="3">
        <text>you</text>
        <sentiments>
          <sentiment polarity="none" sarcasm="no"/>
        </sentiments>
      </entity>
      <entity ere_id="m-261" offset="7483" length="4">
        <text>your</text>
        <sentiments>
          <sentiment polarity="none" sarcasm="no"/>
        </sentiments>
      </entity>
      <entity ere_id="m-267" offset="393" length="21">
        <text>youi blithering idiot</text>
        <sentiments>
          <sentiment polarity="neg" sarcasm="no">
            <source ere_id="m-279" offset="92" length="7">jillian</source>
          </sentiment>
        </sentiments>
      </entity>
      <entity ere_id="m-279" offset="92" length="7">
        <text>jillian</text>
        <sentiments>
          <sentiment polarity="none" sarcasm="no"/>
        </sentiments>
      </entity>
      <entity ere_id="m-285" offset="519" length="3">
        <text>you</text>
        <sentiments>
          <sentiment polarity="none" sarcasm="no"/>
        </sentiments>
      </entity>
      <entity ere_id="m-291" offset="564" length="4">
        <text>your</text>
        <sentiments>
          <sentiment polarity="none" sarcasm="no"/>
        </sentiments>
      </entity>
      <entity ere_id="m-297" offset="590" length="4">
        <text>your</text>
        <sentiments>
          <sentiment polarity="none" sarcasm="no"/>
        </sentiments>
      </entity>
      <entity ere_id="m-303" offset="793" length="2">
        <text>my</text>
        <sentiments>
          <sentiment polarity="none" sarcasm="no"/>
        </sentiments>
      </entity>
      <entity ere_id="m-309" offset="701" length="7">
        <text>jillian</text>
        <sentiments>
          <sentiment polarity="none" sarcasm="no"/>
        </sentiments>
      </entity>
      <entity ere_id="m-315" offset="210" length="5">
        <text>Obama</text>
        <sentiments>
          <sentiment polarity="none" sarcasm="no"/>
        </sentiments>
      </entity>
      <entity ere_id="m-321" offset="285" length="5">
        <text>Obama</text>
        <sentiments>
          <sentiment polarity="none" sarcasm="no"/>
        </sentiments>
      </entity>
      <entity ere_id="m-327" offset="359" length="5">
        <text>obama</text>
        <sentiments>
          <sentiment polarity="none" sarcasm="no"/>
        </sentiments>
      </entity>
      <entity ere_id="m-333" offset="500" length="2">
        <text>he</text>
        <sentiments>
          <sentiment polarity="none" sarcasm="no"/>
        </sentiments>
      </entity>
      <entity ere_id="m-339" offset="756" length="12">
        <text>barack obama</text>
        <sentiments>
          <sentiment polarity="none" sarcasm="no"/>
        </sentiments>
      </entity>
      <entity ere_id="m-345" offset="852" length="2">
        <text>BO</text>
        <sentiments>
          <sentiment polarity="none" sarcasm="no"/>
        </sentiments>
      </entity>
      <entity ere_id="m-351" offset="377" length="14">
        <text>a fed chairman</text>
        <sentiments>
          <sentiment polarity="none" sarcasm="no"/>
        </sentiments>
      </entity>
      <entity ere_id="m-357" offset="423" length="12">
        <text>ben bernanke</text>
        <sentiments>
          <sentiment polarity="none" sarcasm="no"/>
        </sentiments>
      </entity>
      <entity ere_id="m-363" offset="440" length="37">
        <text>the same guy who worked for baby bush</text>
        <sentiments>
          <sentiment polarity="none" sarcasm="no"/>
        </sentiments>
      </entity>
      <entity ere_id="m-369" offset="177" length="14">
        <text>Bernie Sanders</text>
        <sentiments>
          <sentiment polarity="none" sarcasm="no"/>
        </sentiments>
      </entity>
      <entity ere_id="m-375" offset="237" length="7">
        <text>Sanders</text>
        <sentiments>
          <sentiment polarity="none" sarcasm="no"/>
        </sentiments>
      </entity>
      <entity ere_id="m-381" offset="721" length="14">
        <text>bernie sanders</text>
        <sentiments>
          <sentiment polarity="none" sarcasm="no"/>
        </sentiments>
      </entity>
      <entity ere_id="m-387" offset="926" length="7">
        <text>Sanders</text>
        <sentiments>
          <sentiment polarity="none" sarcasm="no"/>
        </sentiments>
      </entity>
      <entity ere_id="m-393" offset="468" length="9">
        <text>baby bush</text>
        <sentiments>
          <sentiment polarity="none" sarcasm="no"/>
        </sentiments>
      </entity>
      <entity ere_id="m-399" offset="808" length="7">
        <text>the o/p</text>
        <sentiments>
          <sentiment polarity="none" sarcasm="no"/>
        </sentiments>
      </entity>
      <entity ere_id="m-405" offset="859" length="19">
        <text>2 communist parents</text>
        <sentiments>
          <sentiment polarity="none" sarcasm="no"/>
        </sentiments>
      </entity>
      <entity ere_id="m-411" offset="1036" length="6">
        <text>sparky</text>
        <sentiments>
          <sentiment polarity="none" sarcasm="no"/>
        </sentiments>
      </entity>
      <entity ere_id="m-417" offset="1188" length="3">
        <text>~S~</text>
        <sentiments>
          <sentiment polarity="none" sarcasm="no"/>
        </sentiments>
      </entity>
      <entity ere_id="m-423" offset="1472" length="3">
        <text>You</text>
        <sentiments>
          <sentiment polarity="none" sarcasm="no"/>
        </sentiments>
      </entity>
      <entity ere_id="m-429" offset="2452" length="3">
        <text>You</text>
        <sentiments>
          <sentiment polarity="none" sarcasm="no"/>
        </sentiments>
      </entity>
      <entity ere_id="m-435" offset="1348" length="4">
        <text>DSGE</text>
        <sentiments>
          <sentiment polarity="none" sarcasm="no"/>
        </sentiments>
      </entity>
      <entity ere_id="m-441" offset="2223" length="4">
        <text>DSGE</text>
        <sentiments>
          <sentiment polarity="none" sarcasm="no"/>
        </sentiments>
      </entity>
      <entity ere_id="m-447" offset="2328" length="4">
        <text>DSGE</text>
        <sentiments>
          <sentiment polarity="none" sarcasm="no"/>
        </sentiments>
      </entity>
      <entity ere_id="m-453" offset="3549" length="4">
        <text>DSGE</text>
        <sentiments>
          <sentiment polarity="none" sarcasm="no"/>
        </sentiments>
      </entity>
      <entity ere_id="m-459" offset="4220" length="1">
        <text>I</text>
        <sentiments>
          <sentiment polarity="none" sarcasm="no"/>
        </sentiments>
      </entity>
      <entity ere_id="m-465" offset="4541" length="4">
        <text>DSGE</text>
        <sentiments>
          <sentiment polarity="none" sarcasm="no"/>
        </sentiments>
      </entity>
      <entity ere_id="m-471" offset="4965" length="1">
        <text>I</text>
        <sentiments>
          <sentiment polarity="none" sarcasm="no"/>
        </sentiments>
      </entity>
      <entity ere_id="m-477" offset="5228" length="3">
        <text>you</text>
        <sentiments>
          <sentiment polarity="none" sarcasm="no"/>
        </sentiments>
      </entity>
      <entity ere_id="m-483" offset="5216" length="3">
        <text>you</text>
        <sentiments>
          <sentiment polarity="none" sarcasm="no"/>
        </sentiments>
      </entity>
      <entity ere_id="m-489" offset="5248" length="3">
        <text>you</text>
        <sentiments>
          <sentiment polarity="none" sarcasm="no"/>
        </sentiments>
      </entity>
      <entity ere_id="m-495" offset="5396" length="4">
        <text>DSGE</text>
        <sentiments>
          <sentiment polarity="none" sarcasm="no"/>
        </sentiments>
      </entity>
      <entity ere_id="m-501" offset="6805" length="4">
        <text>DSGE</text>
        <sentiments>
          <sentiment polarity="none" sarcasm="no"/>
        </sentiments>
      </entity>
      <entity ere_id="m-507" offset="6910" length="4">
        <text>DSGE</text>
        <sentiments>
          <sentiment polarity="none" sarcasm="no"/>
        </sentiments>
      </entity>
      <entity ere_id="m-513" offset="7061" length="1">
        <text>I</text>
        <sentiments>
          <sentiment polarity="none" sarcasm="no"/>
        </sentiments>
      </entity>
      <entity ere_id="m-519" offset="7344" length="3">
        <text>you</text>
        <sentiments>
          <sentiment polarity="none" sarcasm="no"/>
        </sentiments>
      </entity>
      <entity ere_id="m-525" offset="7324" length="3">
        <text>you</text>
        <sentiments>
          <sentiment polarity="none" sarcasm="no"/>
        </sentiments>
      </entity>
      <entity ere_id="m-531" offset="7312" length="3">
        <text>you</text>
        <sentiments>
          <sentiment polarity="none" sarcasm="no"/>
        </sentiments>
      </entity>
      <entity ere_id="m-537" offset="1712" length="8">
        <text>samjones</text>
        <sentiments>
          <sentiment polarity="none" sarcasm="no"/>
        </sentiments>
      </entity>
      <entity ere_id="m-543" offset="3505" length="4">
        <text>your</text>
        <sentiments>
          <sentiment polarity="none" sarcasm="no"/>
        </sentiments>
      </entity>
      <entity ere_id="m-549" offset="2995" length="8">
        <text>samjones</text>
        <sentiments>
          <sentiment polarity="none" sarcasm="no"/>
        </sentiments>
      </entity>
      <entity ere_id="m-555" offset="3654" length="8">
        <text>samjones</text>
        <sentiments>
          <sentiment polarity="none" sarcasm="no"/>
        </sentiments>
      </entity>
      <entity ere_id="m-561" offset="4164" length="4">
        <text>your</text>
        <sentiments>
          <sentiment polarity="none" sarcasm="no"/>
        </sentiments>
      </entity>
      <entity ere_id="m-567" offset="4606" length="8">
        <text>samjones</text>
        <sentiments>
          <sentiment polarity="none" sarcasm="no"/>
        </sentiments>
      </entity>
      <entity ere_id="m-573" offset="4909" length="4">
        <text>your</text>
        <sentiments>
          <sentiment polarity="none" sarcasm="no"/>
        </sentiments>
      </entity>
      <entity ere_id="m-579" offset="7005" length="4">
        <text>your</text>
        <sentiments>
          <sentiment polarity="none" sarcasm="no"/>
        </sentiments>
      </entity>
      <entity ere_id="m-585" offset="5366" length="7">
        <text>Oddball</text>
        <sentiments>
          <sentiment polarity="none" sarcasm="no"/>
        </sentiments>
      </entity>
      <entity ere_id="m-591" offset="5423" length="7">
        <text>Oddball</text>
        <sentiments>
          <sentiment polarity="none" sarcasm="no"/>
        </sentiments>
      </entity>
      <entity ere_id="m-597" offset="5591" length="3">
        <text>you</text>
        <sentiments>
          <sentiment polarity="none" sarcasm="no"/>
        </sentiments>
      </entity>
      <entity ere_id="m-603" offset="5610" length="3">
        <text>You</text>
        <sentiments>
          <sentiment polarity="none" sarcasm="no"/>
        </sentiments>
      </entity>
      <entity ere_id="m-609" offset="5984" length="1">
        <text>I</text>
        <sentiments>
          <sentiment polarity="none" sarcasm="no"/>
        </sentiments>
      </entity>
      <entity ere_id="m-615" offset="5780" length="69">
        <text>some of the greatest authoritarian economic witch doctors of all time</text>
        <sentiments>
          <sentiment polarity="neg" sarcasm="no">
            <source ere_id="m-585" offset="5366" length="7">Oddball</source>
          </sentiment>
        </sentiments>
      </entity>
      <entity ere_id="m-621" offset="5861" length="3">
        <text>FDR</text>
        <sentiments>
          <sentiment polarity="neg" sarcasm="no">
            <source ere_id="m-585" offset="5366" length="7">Oddball</source>
          </sentiment>
        </sentiments>
      </entity>
      <entity ere_id="m-627" offset="5492" length="16">
        <text>those at the Fed</text>
        <sentiments>
          <sentiment polarity="neg" sarcasm="no">
            <source ere_id="m-591" offset="5423" length="7">Oddball</source>
          </sentiment>
        </sentiments>
      </entity>
      <entity ere_id="m-633" offset="5753" length="2">
        <text>He</text>
        <sentiments>
          <sentiment polarity="none" sarcasm="no"/>
        </sentiments>
      </entity>
      <entity ere_id="m-639" offset="5883" length="8">
        <text>Friedman</text>
        <sentiments>
          <sentiment polarity="none" sarcasm="no"/>
        </sentiments>
      </entity>
      <entity ere_id="m-645" offset="5919" length="2">
        <text>he</text>
        <sentiments>
          <sentiment polarity="none" sarcasm="no"/>
        </sentiments>
      </entity>
      <entity ere_id="m-651" offset="6001" length="8">
        <text>Friedman</text>
        <sentiments>
          <sentiment polarity="none" sarcasm="no"/>
        </sentiments>
      </entity>
      <entity ere_id="m-657" offset="5620" length="15">
        <text>Milton Friedman</text>
        <sentiments>
          <sentiment polarity="none" sarcasm="no"/>
        </sentiments>
      </entity>
      <entity ere_id="m-663" offset="6161" length="8">
        <text>Friedman</text>
        <sentiments>
          <sentiment polarity="none" sarcasm="no"/>
        </sentiments>
      </entity>
      <entity ere_id="m-669" offset="6049" length="8">
        <text>Friedman</text>
        <sentiments>
          <sentiment polarity="none" sarcasm="no"/>
        </sentiments>
      </entity>
      <entity ere_id="m-675" offset="6344" length="30">
        <text>most all modern day economists</text>
        <sentiments>
          <sentiment polarity="none" sarcasm="no"/>
        </sentiments>
      </entity>
      <entity ere_id="m-681" offset="6393" length="4">
        <text>they</text>
        <sentiments>
          <sentiment polarity="none" sarcasm="no"/>
        </sentiments>
      </entity>
      <entity ere_id="m-687" offset="6581" length="4">
        <text>they</text>
        <sentiments>
          <sentiment polarity="none" sarcasm="no"/>
        </sentiments>
      </entity>
      <entity ere_id="m-1312" offset="6535" length="5">
        <text>their</text>
        <sentiments>
          <sentiment polarity="none" sarcasm="no"/>
        </sentiments>
      </entity>
      <entity ere_id="m-693" offset="6215" length="6">
        <text>Keynes</text>
        <sentiments>
          <sentiment polarity="none" sarcasm="no"/>
        </sentiments>
      </entity>
      <entity ere_id="m-699" offset="6247" length="3">
        <text>his</text>
        <sentiments>
          <sentiment polarity="none" sarcasm="no"/>
        </sentiments>
      </entity>
      <entity ere_id="m-705" offset="6324" length="2">
        <text>he</text>
        <sentiments>
          <sentiment polarity="none" sarcasm="no"/>
        </sentiments>
      </entity>
      <entity ere_id="m-711" offset="6231" length="2">
        <text>He</text>
        <sentiments>
          <sentiment polarity="none" sarcasm="no"/>
        </sentiments>
      </entity>
      <entity ere_id="m-717" offset="6234" length="7">
        <text>himself</text>
        <sentiments>
          <sentiment polarity="none" sarcasm="no"/>
        </sentiments>
      </entity>
      <entity ere_id="m-723" offset="5290" length="13">
        <text>TakeAStepBack</text>
        <sentiments>
          <sentiment polarity="none" sarcasm="no"/>
        </sentiments>
      </entity>
      <entity ere_id="m-729" offset="6122" length="8">
        <text>Pinochet</text>
        <sentiments>
          <sentiment polarity="none" sarcasm="no"/>
        </sentiments>
      </entity>
      <entity ere_id="m-735" offset="6076" length="12">
        <text>Chicago boys</text>
        <sentiments>
          <sentiment polarity="none" sarcasm="no"/>
        </sentiments>
      </entity>
      <entity ere_id="m-273" offset="7038" length="3">
        <text>You</text>
        <sentiments>
          <sentiment polarity="none" sarcasm="no"/>
        </sentiments>
      </entity>
      <entity ere_id="m-741" offset="258" length="6">
        <text>Senate</text>
        <sentiments>
          <sentiment polarity="none" sarcasm="no"/>
        </sentiments>
      </entity>
      <entity ere_id="m-747" offset="334" length="3">
        <text>Fed</text>
        <sentiments>
          <sentiment polarity="none" sarcasm="no"/>
        </sentiments>
      </entity>
      <entity ere_id="m-753" offset="379" length="3">
        <text>fed</text>
        <sentiments>
          <sentiment polarity="none" sarcasm="no"/>
        </sentiments>
      </entity>
      <entity ere_id="m-759" offset="1055" length="3">
        <text>Fed</text>
        <sentiments>
          <sentiment polarity="none" sarcasm="no"/>
        </sentiments>
      </entity>
      <entity ere_id="m-765" offset="5505" length="3">
        <text>Fed</text>
        <sentiments>
          <sentiment polarity="none" sarcasm="no"/>
        </sentiments>
      </entity>
      <entity ere_id="m-771" offset="5958" length="10">
        <text>the nation</text>
        <sentiments>
          <sentiment polarity="none" sarcasm="no"/>
        </sentiments>
      </entity>
      <entity ere_id="m-777" offset="6076" length="7">
        <text>Chicago</text>
        <sentiments>
          <sentiment polarity="none" sarcasm="no"/>
        </sentiments>
      </entity>
      <entity ere_id="m-783" offset="6106" length="13">
        <text>south America</text>
        <sentiments>
          <sentiment polarity="none" sarcasm="no"/>
        </sentiments>
      </entity>
      <entity ere_id="m-877" offset="6132" length="6">
        <text>anyone</text>
        <sentiments>
          <sentiment polarity="none" sarcasm="no"/>
        </sentiments>
      </entity>
      <entity ere_id="m-886" offset="156" length="2">
        <text>we</text>
        <sentiments>
          <sentiment polarity="none" sarcasm="no"/>
        </sentiments>
      </entity>
      <entity ere_id="m-895" offset="275" length="2">
        <text>us</text>
        <sentiments>
          <sentiment polarity="none" sarcasm="no"/>
        </sentiments>
      </entity>
      <entity ere_id="m-975" offset="1231" length="2">
        <text>us</text>
        <sentiments>
          <sentiment polarity="none" sarcasm="no"/>
        </sentiments>
      </entity>
      <entity ere_id="m-1041" offset="3488" length="2">
        <text>us</text>
        <sentiments>
          <sentiment polarity="none" sarcasm="no"/>
        </sentiments>
      </entity>
      <entity ere_id="m-1059" offset="4147" length="2">
        <text>us</text>
        <sentiments>
          <sentiment polarity="none" sarcasm="no"/>
        </sentiments>
      </entity>
      <entity ere_id="m-1071" offset="4892" length="2">
        <text>us</text>
        <sentiments>
          <sentiment polarity="none" sarcasm="no"/>
        </sentiments>
      </entity>
      <entity ere_id="m-1083" offset="5525" length="2">
        <text>us</text>
        <sentiments>
          <sentiment polarity="none" sarcasm="no"/>
        </sentiments>
      </entity>
      <entity ere_id="m-1125" offset="6988" length="2">
        <text>us</text>
        <sentiments>
          <sentiment polarity="none" sarcasm="no"/>
        </sentiments>
      </entity>
      <entity ere_id="m-1140" offset="7477" length="2">
        <text>us</text>
        <sentiments>
          <sentiment polarity="none" sarcasm="no"/>
        </sentiments>
      </entity>
      <entity ere_id="m-901" offset="311" length="35">
        <text>a liberal inflationist Fed Chairman</text>
        <sentiments>
          <sentiment polarity="none" sarcasm="no"/>
        </sentiments>
      </entity>
      <entity ere_id="m-954" offset="1087" length="5">
        <text>their</text>
        <sentiments>
          <sentiment polarity="none" sarcasm="no"/>
        </sentiments>
      </entity>
      <entity ere_id="m-966" offset="1141" length="7">
        <text>a world</text>
        <sentiments>
          <sentiment polarity="none" sarcasm="no"/>
        </sentiments>
      </entity>
      <entity ere_id="m-981" offset="1532" length="41">
        <text>everyone who has gotten as far as college</text>
        <sentiments>
          <sentiment polarity="none" sarcasm="no"/>
        </sentiments>
      </entity>
      <entity ere_id="m-990" offset="1801" length="41">
        <text>everyone who has gotten as far as college</text>
        <sentiments>
          <sentiment polarity="none" sarcasm="no"/>
        </sentiments>
      </entity>
      <entity ere_id="m-1005" offset="2512" length="41">
        <text>everyone who has gotten as far as college</text>
        <sentiments>
          <sentiment polarity="none" sarcasm="no"/>
        </sentiments>
      </entity>
      <entity ere_id="m-1020" offset="2774" length="42">
        <text>everybody who has gotten as far as college</text>
        <sentiments>
          <sentiment polarity="none" sarcasm="no"/>
        </sentiments>
      </entity>
      <entity ere_id="m-1029" offset="3044" length="41">
        <text>everyone who has gotten as far as college</text>
        <sentiments>
          <sentiment polarity="none" sarcasm="no"/>
        </sentiments>
      </entity>
      <entity ere_id="m-1047" offset="3703" length="41">
        <text>everyone who has gotten as far as college</text>
        <sentiments>
          <sentiment polarity="none" sarcasm="no"/>
        </sentiments>
      </entity>
      <entity ere_id="m-996" offset="1979" length="17">
        <text>quite a few of us</text>
        <sentiments>
          <sentiment polarity="none" sarcasm="no"/>
        </sentiments>
      </entity>
      <entity ere_id="m-1035" offset="3222" length="17">
        <text>quite a few of us</text>
        <sentiments>
          <sentiment polarity="none" sarcasm="no"/>
        </sentiments>
      </entity>
      <entity ere_id="m-1053" offset="3881" length="17">
        <text>quite a few of us</text>
        <sentiments>
          <sentiment polarity="none" sarcasm="no"/>
        </sentiments>
      </entity>
      <entity ere_id="m-1065" offset="4626" length="17">
        <text>quite a few of us</text>
        <sentiments>
          <sentiment polarity="none" sarcasm="no"/>
        </sentiments>
      </entity>
      <entity ere_id="m-1011" offset="2755" length="12">
        <text>other people</text>
        <sentiments>
          <sentiment polarity="none" sarcasm="no"/>
        </sentiments>
      </entity>
      <entity ere_id="m-1077" offset="5447" length="38">
        <text>monetary central planner witch doctors</text>
        <sentiments>
          <sentiment polarity="neg" sarcasm="no">
            <source ere_id="m-591" offset="5423" length="7">Oddball</source>
          </sentiment>
        </sentiments>
      </entity>
      <entity ere_id="m-1089" offset="5533" length="3">
        <text>you</text>
        <sentiments>
          <sentiment polarity="none" sarcasm="no"/>
        </sentiments>
      </entity>
      <entity ere_id="m-1098" offset="6282" length="31">
        <text>authoritarian style governments</text>
        <sentiments>
          <sentiment polarity="none" sarcasm="no"/>
        </sentiments>
      </entity>
      <entity ere_id="m-1107" offset="6646" length="8">
        <text> a human</text>
        <sentiments>
          <sentiment polarity="none" sarcasm="no"/>
        </sentiments>
      </entity>
      <entity ere_id="m-1116" offset="6708" length="11">
        <text>Monetarists</text>
        <sentiments>
          <sentiment polarity="none" sarcasm="no"/>
        </sentiments>
      </entity>
      <entity ere_id="m-1134" offset="7425" length="9">
        <text>everybody</text>
        <sentiments>
          <sentiment polarity="none" sarcasm="no"/>
        </sentiments>
      </entity>
      <entity ere_id="m-1146" offset="7551" length="7">
        <text>anybody</text>
        <sentiments>
          <sentiment polarity="none" sarcasm="no"/>
        </sentiments>
      </entity>
      <entity ere_id="m-1155" offset="1566" length="7">
        <text>college</text>
        <sentiments>
          <sentiment polarity="none" sarcasm="no"/>
        </sentiments>
      </entity>
      <entity ere_id="m-1164" offset="1835" length="7">
        <text>college</text>
        <sentiments>
          <sentiment polarity="none" sarcasm="no"/>
        </sentiments>
      </entity>
      <entity ere_id="m-1170" offset="2546" length="7">
        <text>college</text>
        <sentiments>
          <sentiment polarity="none" sarcasm="no"/>
        </sentiments>
      </entity>
      <entity ere_id="m-1176" offset="2809" length="7">
        <text>college</text>
        <sentiments>
          <sentiment polarity="none" sarcasm="no"/>
        </sentiments>
      </entity>
      <entity ere_id="m-1182" offset="3078" length="7">
        <text>college</text>
        <sentiments>
          <sentiment polarity="none" sarcasm="no"/>
        </sentiments>
      </entity>
      <entity ere_id="m-1188" offset="3737" length="7">
        <text>college</text>
        <sentiments>
          <sentiment polarity="none" sarcasm="no"/>
        </sentiments>
      </entity>
      <entity ere_id="m-1194" offset="7444" length="7">
        <text>college</text>
        <sentiments>
          <sentiment polarity="none" sarcasm="no"/>
        </sentiments>
      </entity>
      <entity ere_id="m-1200" offset="4663" length="7">
        <text>college</text>
        <sentiments>
          <sentiment polarity="none" sarcasm="no"/>
        </sentiments>
      </entity>
      <entity ere_id="m-1206" offset="3259" length="7">
        <text>college</text>
        <sentiments>
          <sentiment polarity="none" sarcasm="no"/>
        </sentiments>
      </entity>
      <entity ere_id="m-1212" offset="3918" length="7">
        <text>college</text>
        <sentiments>
          <sentiment polarity="none" sarcasm="no"/>
        </sentiments>
      </entity>
      <entity ere_id="m-1218" offset="2700" length="7">
        <text>college</text>
        <sentiments>
          <sentiment polarity="none" sarcasm="no"/>
        </sentiments>
      </entity>
      <entity ere_id="m-1224" offset="2016" length="7">
        <text>college</text>
        <sentiments>
          <sentiment polarity="none" sarcasm="no"/>
        </sentiments>
      </entity>
      <entity ere_id="m-1280" offset="278" length="3">
        <text>all</text>
        <sentiments>
          <sentiment polarity="none" sarcasm="no"/>
        </sentiments>
      </entity>
      <entity ere_id="m-1332" offset="5788" length="61">
        <text>the greatest authoritarian economic witch doctors of all time</text>
        <sentiments>
          <sentiment polarity="neg" sarcasm="no">
            <source ere_id="m-585" offset="5366" length="7">Oddball</source>
          </sentiment>
        </sentiments>
      </entity>
    </entities>
    <relations>
      <relation ere_id="relm-789">
        <trigger offset="251" length="2">in</trigger>
        <sentiments>
          <sentiment polarity="none" sarcasm="no"/>
        </sentiments>
      </relation>
      <relation ere_id="relm-799">
        <trigger offset="383" length="8">chairman</trigger>
        <sentiments>
          <sentiment polarity="none" sarcasm="no"/>
        </sentiments>
      </relation>
      <relation ere_id="relm-809">
        <trigger offset="464" length="3">for</trigger>
        <sentiments>
          <sentiment polarity="none" sarcasm="no"/>
        </sentiments>
      </relation>
      <relation ere_id="relm-819">
        <trigger offset="871" length="7">parents</trigger>
        <sentiments>
          <sentiment polarity="none" sarcasm="no"/>
        </sentiments>
      </relation>
      <relation ere_id="relm-829">
        <trigger offset="5498" length="2">at</trigger>
        <sentiments>
          <sentiment polarity="none" sarcasm="no"/>
        </sentiments>
      </relation>
      <relation ere_id="relm-839">
        <trigger offset="5763" length="4">with</trigger>
        <sentiments>
          <sentiment polarity="neg" sarcasm="no">
            <source ere_id="m-585" offset="5366" length="7">Oddball</source>
          </sentiment>
        </sentiments>
      </relation>
      <relation ere_id="relm-907">
        <trigger offset="338" length="8">Chairman</trigger>
        <sentiments>
          <sentiment polarity="none" sarcasm="no"/>
        </sentiments>
      </relation>
      <relation ere_id="relm-1230">
        <trigger offset="1997" length="6">got to</trigger>
        <sentiments>
          <sentiment polarity="none" sarcasm="no"/>
        </sentiments>
      </relation>
      <relation ere_id="relm-1240">
        <trigger offset="3240" length="6">got to</trigger>
        <sentiments>
          <sentiment polarity="none" sarcasm="no"/>
        </sentiments>
      </relation>
      <relation ere_id="relm-1250">
        <trigger offset="3899" length="6">got to</trigger>
        <sentiments>
          <sentiment polarity="none" sarcasm="no"/>
        </sentiments>
      </relation>
      <relation ere_id="relm-1260">
        <trigger offset="4644" length="6">got to</trigger>
        <sentiments>
          <sentiment polarity="none" sarcasm="no"/>
        </sentiments>
      </relation>
      <relation ere_id="relm-1270">
        <trigger offset="7438" length="5">go to</trigger>
        <sentiments>
          <sentiment polarity="none" sarcasm="no"/>
        </sentiments>
      </relation>
    </relations>
    <events>
      <event ere_id="em-849">
        <trigger offset="369" length="7">appoint</trigger>
        <sentiments>
          <sentiment polarity="none" sarcasm="no"/>
        </sentiments>
      </event>
      <event ere_id="em-917">
        <trigger offset="515" length="3">pay</trigger>
        <sentiments>
          <sentiment polarity="none" sarcasm="no"/>
        </sentiments>
      </event>
      <event ere_id="em-1289">
        <trigger offset="303" length="7">appoint</trigger>
        <sentiments>
          <sentiment polarity="none" sarcasm="no"/>
        </sentiments>
      </event>
    </events>
  </sentiment_annotations>
</belief_sentiment_doc>
