<?xml version="1.0" encoding="UTF-8"?>
<deft_ere kit_id="568eb23c0000000000000015" doc_id="ENG_DF_000183_20150408_F0000009B_11977-13151" source_type="multi_post">
  <entities>
    <entity id="ent-m.0by04" type="FAC" specificity="specific">
      <entity_mention id="m-568eb23c_15_45" noun_type="NAM" source="ENG_DF_000183_20150408_F0000009B" offset="12844" length="31">
        <mention_text>United States Naval Observatory</mention_text>
      </entity_mention>
    </entity>
    <entity id="ent-m.023wv_" type="FAC" specificity="specific">
      <entity_mention id="m-568eb23c_15_51" noun_type="NAM" source="ENG_DF_000183_20150408_F0000009B" offset="12777" length="29">
        <mention_text>Number One Observatory Circle</mention_text>
      </entity_mention>
    </entity>
    <entity id="ent-m.0157m" type="PER" specificity="specific">
      <entity_mention id="m-568eb23c_15_57" noun_type="NAM" source="ENG_DF_000183_20150408_F0000009B" offset="12748" length="12">
        <mention_text>Bill Clinton</mention_text>
      </entity_mention>
      <entity_mention id="m-568eb23c_15_63" noun_type="NAM" source="ENG_DF_000183_20150408_F0000009B" offset="12947" length="4">
        <mention_text>Bill</mention_text>
      </entity_mention>
    </entity>
    <entity id="ent-m.0d06m5" type="PER" specificity="specific">
      <entity_mention id="m-568eb23c_15_69" noun_type="NAM" source="ENG_DF_000183_20150408_F0000009B" offset="12549" length="7">
        <mention_text>Clinton</mention_text>
      </entity_mention>
      <entity_mention id="m-568eb23c_15_75" noun_type="NAM" source="ENG_DF_000183_20150408_F0000009B" offset="12688" length="15">
        <mention_text>Hillary Clinton</mention_text>
      </entity_mention>
    </entity>
    <entity id="ent-m.07wbk" type="ORG" specificity="specific">
      <entity_mention id="m-568eb23c_15_81" noun_type="NAM" source="ENG_DF_000183_20150408_F0000009B" offset="12417" length="3">
        <mention_text>GOP</mention_text>
      </entity_mention>
    </entity>
    <entity id="ent-NIL01069" type="PER" specificity="specific">
      <entity_mention id="m-568eb23c_15_87" noun_type="NAM" source="ENG_DF_000183_20150408_F0000009B" offset="12187" length="14">
        <mention_text>MastersNemesis</mention_text>
      </entity_mention>
      <entity_mention id="m-568eb23c_15_93" noun_type="NAM" source="ENG_DF_000183_20150408_F0000009B" offset="12292" length="17">
        <mention_text>TheMastersNemesis</mention_text>
      </entity_mention>
      <entity_mention id="m-568eb23c_15_150" noun_type="PRO" source="ENG_DF_000183_20150408_F0000009B" offset="12165" length="3">
        <mention_text>You</mention_text>
      </entity_mention>
      <entity_mention id="m-568eb23c_15_156" noun_type="PRO" source="ENG_DF_000183_20150408_F0000009B" offset="12228" length="3">
        <mention_text>you</mention_text>
      </entity_mention>
      <entity_mention id="m-568eb23c_15_162" noun_type="PRO" source="ENG_DF_000183_20150408_F0000009B" offset="12347" length="1">
        <mention_text>I</mention_text>
      </entity_mention>
    </entity>
    <entity id="ent-NIL01085" type="PER" specificity="specific">
      <entity_mention id="m-568eb23c_15_99" noun_type="NAM" source="ENG_DF_000183_20150408_F0000009B" offset="12000" length="13">
        <mention_text>Major Hogwash</mention_text>
      </entity_mention>
      <entity_mention id="m-568eb23c_15_123" noun_type="PRO" source="ENG_DF_000183_20150408_F0000009B" offset="12051" length="1">
        <mention_text>I</mention_text>
      </entity_mention>
      <entity_mention id="m-568eb23c_15_138" noun_type="PRO" source="ENG_DF_000183_20150408_F0000009B" offset="12111" length="1">
        <mention_text>I</mention_text>
      </entity_mention>
      <entity_mention id="m-568eb23c_15_144" noun_type="PRO" source="ENG_DF_000183_20150408_F0000009B" offset="12144" length="2">
        <mention_text>my</mention_text>
      </entity_mention>
    </entity>
    <entity id="ent-NIL01089" type="PER" specificity="specific">
      <entity_mention id="m-568eb23c_15_105" noun_type="NAM" source="ENG_DF_000183_20150408_F0000009B" offset="13027" length="10">
        <mention_text>Glassunion</mention_text>
      </entity_mention>
    </entity>
    <entity id="ent-NIL01091" type="PER" specificity="specific">
      <entity_mention id="m-568eb23c_15_111" noun_type="NAM" source="ENG_DF_000183_20150408_F0000009B" offset="12481" length="17">
        <mention_text>Tierra_y_Libertad</mention_text>
      </entity_mention>
    </entity>
    <entity id="ent-NIL01092" type="PER" specificity="specific">
      <entity_mention id="m-568eb23c_15_117" noun_type="NAM" source="ENG_DF_000183_20150408_F0000009B" offset="12624" length="6">
        <mention_text>EL34x4</mention_text>
      </entity_mention>
    </entity>
    <entity id="ent-568eb23c_15_135" type="PER" specificity="nonspecific">
      <entity_mention id="m-568eb23c_15_129" noun_type="PRO" source="ENG_DF_000183_20150408_F0000009B" offset="12069" length="7">
        <mention_text>someone</mention_text>
      </entity_mention>
    </entity>
    <entity id="ent-568eb23c_15_174" type="PER" specificity="nonspecific">
      <entity_mention id="m-568eb23c_15_168" noun_type="NOM" source="ENG_DF_000183_20150408_F0000009B" offset="12427" length="2">
        <mention_text>RW</mention_text>
        <nom_head source="ENG_DF_000183_20150408_F0000009B" offset="12427" length="2">RW</nom_head>
      </entity_mention>
    </entity>
    <entity id="ent-568eb23c_15_183" type="FAC" specificity="specific">
      <entity_mention id="m-568eb23c_15_177" noun_type="NAM" source="ENG_DF_000183_20150408_F0000009B" offset="12717" length="11">
        <mention_text>White House</mention_text>
      </entity_mention>
    </entity>
    <entity id="ent-568eb23c_15_192" type="PER" specificity="nonspecific">
      <entity_mention id="m-568eb23c_15_186" noun_type="NOM" source="ENG_DF_000183_20150408_F0000009B" offset="12808" length="6">
        <mention_text>the VP</mention_text>
        <nom_head source="ENG_DF_000183_20150408_F0000009B" offset="12812" length="2">VP</nom_head>
      </entity_mention>
    </entity>
    <entity id="ent-568eb23c_15_201" type="FAC" specificity="specific">
      <entity_mention id="m-568eb23c_15_195" noun_type="NOM" source="ENG_DF_000183_20150408_F0000009B" offset="12825" length="50">
        <mention_text>the grounds of the United States Naval Observatory</mention_text>
        <nom_head source="ENG_DF_000183_20150408_F0000009B" offset="12829" length="7">grounds</nom_head>
      </entity_mention>
    </entity>
    <entity id="ent-568eb23c_15_210" type="GPE" specificity="specific">
      <entity_mention id="m-568eb23c_15_204" noun_type="NAM" source="ENG_DF_000183_20150408_F0000009B" offset="12844" length="13">
        <mention_text>United States</mention_text>
      </entity_mention>
    </entity>
    <entity id="ent-568eb23c_15_219" type="ORG" specificity="specific">
      <entity_mention id="m-568eb23c_15_213" noun_type="NAM" source="ENG_DF_000183_20150408_F0000009B" offset="12844" length="19">
        <mention_text>United States Naval</mention_text>
      </entity_mention>
    </entity>
    <entity id="ent-568eb23c_15_228" type="PER" specificity="specific">
      <entity_mention id="m-568eb23c_15_222" noun_type="PRO" source="ENG_DF_000183_20150408_F0000009B" offset="12911" length="4">
        <mention_text>they</mention_text>
      </entity_mention>
    </entity>
  </entities>
  <fillers>
    <filler id="f-568eb23c_15_239" source="ENG_DF_000183_20150408_F0000009B" offset="12678" length="9" type="title">President</filler>
    <filler id="f-568eb23c_15_259" source="ENG_DF_000183_20150408_F0000009B" offset="12733" length="14" type="title">Vice President</filler>
  </fillers>
  <relations>
    <relation id="r-139" type="personalsocial" subtype="role">
      <relation_mention id="relm-568eb23c_15_231" realis="false">
        <rel_arg1 entity_id="ent-m.0d06m5" entity_mention_id="m-568eb23c_15_75" role="per">Hillary Clinton</rel_arg1>
        <rel_arg2 filler_id="f-568eb23c_15_239" role="role">President</rel_arg2>
      </relation_mention>
    </relation>
    <relation id="r-140" type="physical" subtype="resident">
      <relation_mention id="relm-568eb23c_15_241" realis="false">
        <rel_arg1 entity_id="ent-m.0d06m5" entity_mention_id="m-568eb23c_15_75" role="per">Hillary Clinton</rel_arg1>
        <rel_arg2 entity_id="ent-568eb23c_15_183" entity_mention_id="m-568eb23c_15_177" role="loc">White House</rel_arg2>
        <trigger source="ENG_DF_000183_20150408_F0000009B" offset="12704" length="5">lived</trigger>
      </relation_mention>
    </relation>
    <relation id="r-141" type="personalsocial" subtype="role">
      <relation_mention id="relm-568eb23c_15_251" realis="false">
        <rel_arg1 entity_id="ent-m.0157m" entity_mention_id="m-568eb23c_15_57" role="per">Bill Clinton</rel_arg1>
        <rel_arg2 filler_id="f-568eb23c_15_259" role="role">Vice President</rel_arg2>
      </relation_mention>
    </relation>
    <relation id="r-142" type="physical" subtype="resident">
      <relation_mention id="relm-568eb23c_15_261" realis="false">
        <rel_arg1 entity_id="ent-m.0157m" entity_mention_id="m-568eb23c_15_57" role="per">Bill Clinton</rel_arg1>
        <rel_arg2 entity_id="ent-m.023wv_" entity_mention_id="m-568eb23c_15_51" role="loc">Number One Observatory Circle</rel_arg2>
        <trigger source="ENG_DF_000183_20150408_F0000009B" offset="12767" length="6">reside</trigger>
      </relation_mention>
    </relation>
    <relation id="r-143" type="physical" subtype="resident">
      <relation_mention id="relm-568eb23c_15_271" realis="true">
        <rel_arg1 entity_id="ent-568eb23c_15_192" entity_mention_id="m-568eb23c_15_186" role="per">the VP</rel_arg1>
        <rel_arg2 entity_id="ent-m.023wv_" entity_mention_id="m-568eb23c_15_51" role="loc">Number One Observatory Circle</rel_arg2>
        <trigger source="ENG_DF_000183_20150408_F0000009B" offset="12817" length="4">home</trigger>
      </relation_mention>
    </relation>
    <relation id="r-144" type="physical" subtype="locatednear">
      <relation_mention id="relm-568eb23c_15_281" realis="true">
        <rel_arg1 entity_id="ent-m.023wv_" entity_mention_id="m-568eb23c_15_51" role="entity">Number One Observatory Circle</rel_arg1>
        <rel_arg2 entity_id="ent-568eb23c_15_201" entity_mention_id="m-568eb23c_15_195" role="loc">the grounds of the United States Naval Observatory</rel_arg2>
        <trigger source="ENG_DF_000183_20150408_F0000009B" offset="12822" length="2">on</trigger>
      </relation_mention>
    </relation>
    <relation id="r-145" type="physical" subtype="locatednear">
      <relation_mention id="relm-568eb23c_15_291" realis="true">
        <rel_arg1 entity_id="ent-m.0by04" entity_mention_id="m-568eb23c_15_45" role="entity">United States Naval Observatory</rel_arg1>
        <rel_arg2 entity_id="ent-568eb23c_15_201" entity_mention_id="m-568eb23c_15_195" role="loc">the grounds of the United States Naval Observatory</rel_arg2>
        <trigger source="ENG_DF_000183_20150408_F0000009B" offset="12837" length="2">of</trigger>
      </relation_mention>
    </relation>
    <relation id="r-146" type="partwhole" subtype="subsidiary">
      <relation_mention id="relm-568eb23c_15_301" realis="true">
        <rel_arg1 entity_id="ent-568eb23c_15_219" entity_mention_id="m-568eb23c_15_213" role="suborg">United States Naval</rel_arg1>
        <rel_arg2 entity_id="ent-568eb23c_15_210" entity_mention_id="m-568eb23c_15_204" role="parent">United States</rel_arg2>
      </relation_mention>
    </relation>
    <relation id="r-147" type="physical" subtype="orglocationorigin">
      <relation_mention id="relm-568eb23c_15_321" realis="true">
        <rel_arg1 entity_id="ent-568eb23c_15_219" entity_mention_id="m-568eb23c_15_213" role="org">United States Naval</rel_arg1>
        <rel_arg2 entity_id="ent-m.0by04" entity_mention_id="m-568eb23c_15_45" role="loc">United States Naval Observatory</rel_arg2>
      </relation_mention>
    </relation>
  </relations>
  <hoppers>
    <hopper id="h-568eb23c_15_16">
      <event_mention id="em-568eb23c_15_331" type="contact" subtype="correspondence" realis="actual" audience="twoway" formality="informal" medium="notinperson" schedule="spontaneous">
        <trigger source="ENG_DF_000183_20150408_F0000009B" offset="12091" length="10">discussion</trigger>
        <em_arg entity_id="ent-568eb23c_15_135" entity_mention_id="m-568eb23c_15_129" role="entity" realis="true">someone</em_arg>
        <em_arg entity_id="ent-NIL01085" entity_mention_id="m-568eb23c_15_123" role="entity" realis="true">I</em_arg>
      </event_mention>
    </hopper>
    <hopper id="h-568eb23c_15_380">
      <event_mention id="em-568eb23c_15_359" type="contact" subtype="meet" realis="generic" audience="twoway" formality="formal" medium="inperson" schedule="planned">
        <trigger source="ENG_DF_000183_20150408_F0000009B" offset="12929" length="6">appear</trigger>
        <em_arg entity_id="ent-568eb23c_15_228" entity_mention_id="m-568eb23c_15_222" role="entity" realis="true">they</em_arg>
      </event_mention>
    </hopper>
  </hoppers>
</deft_ere>
